setup.py
tap_framework/__init__.py
tap_framework/client.py
tap_framework/config.py
tap_framework/schemas.py
tap_framework/state.py
tap_framework/streams.py
tap_framework.egg-info/PKG-INFO
tap_framework.egg-info/SOURCES.txt
tap_framework.egg-info/dependency_links.txt
tap_framework.egg-info/requires.txt
tap_framework.egg-info/top_level.txt