Metadata-Version: 1.1
Name: tap-framework
Version: 0.1.0
Summary: Framework for building Singer.io taps
Home-page: http://fishtownanalytics.com
Author: Fishtown Analytics
Author-email: UNKNOWN
License: UNKNOWN
Platform: UNKNOWN
Classifier: Programming Language :: Python :: 3 :: Only
